bitwarden/kalledk/__init__.py
bitwarden/kalledk/py.typed
bitwarden_kalledk-0.1.2.dist-info/METADATA
bitwarden_kalledk-0.1.2.dist-info/WHEEL
bitwarden_kalledk-0.1.2.dist-info/licenses/LICENSE
bitwarden_kalledk-0.1.2.dist-info/RECORD
