Metadata-Version: 2.4
Name: bitwarden-kalledk
Version: 0.1.2
Summary: Bitwarden Overlay
Project-URL: Homepage, https://github.com/KalleDK/py-bitwarden-kalledk
Project-URL: Documentation, https://github.com/KalleDK/py-bitwarden-kalledk
Project-URL: Repository, https://github.com/KalleDK/py-bitwarden-kalledk.git
Author-email: "Kalle M. Aagaard" <git@k-moeller.dk>
Maintainer-email: "Kalle M. Aagaard" <git@k-moeller.dk>
License-File: LICENSE
Classifier: License :: OSI Approved :: MIT License
Classifier: Programming Language :: Python :: 3.14
Requires-Python: >=3.14
